Workbook

Sheet Summary
A1: AAIP Lead Organization Budget Summary | B1: AAIP Lead Organization Budget Summary | C1: AAIP Lead Organization Budget Summary | D1: AAIP Lead Organization Budget Summary | E1: AAIP Lead Organization Budget Summary | F1: AAIP Lead Organization Budget Summary | G1: AAIP Lead Organization Budget Summary | H1: AAIP Lead Organization Budget Summary
A2: NSF 26-509 Category II: Indigenous Data Commons | B2: NSF 26-509 Category II: Indigenous Data Commons | C2: NSF 26-509 Category II: Indigenous Data Commons | D2: NSF 26-509 Category II: Indigenous Data Commons | E2: NSF 26-509 Category II: Indigenous Data Commons | F2: NSF 26-509 Category II: Indigenous Data Commons | G2: NSF 26-509 Category II: Indigenous Data Commons | H2: NSF 26-509 Category II: Indigenous Data Commons
A4: Budget Component | B4: Year 1 | C4: Year 2 | D4: Year 3 | E4: Total
A5: Salaries & Wages | B5: ='AAIP Budget'!G15 -> 527000 | C5: ='AAIP Budget'!H15 -> 542810 | D5: ='AAIP Budget'!I15 -> 559094.3 | E5: =SUM(B5:D5) -> 1628904.3
A6: Fringe Benefits | B6: ='AAIP Budget'!G16 -> 131750 | C6: ='AAIP Budget'!H16 -> 135702.5 | D6: ='AAIP Budget'!I16 -> 139773.58 | E6: =SUM(B6:D6) -> 407226.08
A7: Travel | B7: =SUM('AAIP Budget'!G18:G20) -> 80000 | C7: =SUM('AAIP Budget'!H18:H20) -> 65000 | D7: =SUM('AAIP Budget'!I18:I20) -> 55000 | E7: =SUM(B7:D7) -> 200000
A8: Participant Support | B8: ='AAIP Budget'!G21 -> 75000 | C8: ='AAIP Budget'!H21 -> 75000 | D8: ='AAIP Budget'!I21 -> 75000 | E8: =SUM(B8:D8) -> 225000
A9: Equipment | B9: ='AAIP Budget'!G22 -> 75000 | C9: ='AAIP Budget'!H22 -> 0 | D9: ='AAIP Budget'!I22 -> 0 | E9: =SUM(B9:D9) -> 75000
A10: Materials & Supplies | B10: ='AAIP Budget'!G23 -> 20000 | C10: ='AAIP Budget'!H23 -> 10000 | D10: ='AAIP Budget'!I23 -> 10000 | E10: =SUM(B10:D10) -> 40000
A11: Publication/Documentation/Dissemination | B11: ='AAIP Budget'!G24 -> 20000 | C11: ='AAIP Budget'!H24 -> 30000 | D11: ='AAIP Budget'!I24 -> 30000 | E11: =SUM(B11:D11) -> 80000
A12: Consultant Services | B12: =SUM('AAIP Budget'!G25:G27) -> 90000 | C12: =SUM('AAIP Budget'!H25:H27) -> 60000 | D12: =SUM('AAIP Budget'!I25:I27) -> 50000 | E12: =SUM(B12:D12) -> 200000
A13: Computer Services | B13: =SUM('AAIP Budget'!G28:G32) -> 345000 | C13: =SUM('AAIP Budget'!H28:H32) -> 220000 | D13: =SUM('AAIP Budget'!I28:I32) -> 180000 | E13: =SUM(B13:D13) -> 745000
A14: Other Direct Costs | B14: =SUM('AAIP Budget'!G33:G35) -> 30000 | C14: =SUM('AAIP Budget'!H33:H35) -> 25000 | D14: =SUM('AAIP Budget'!I33:I35) -> 25000 | E14: =SUM(B14:D14) -> 80000
A15: Indirect Costs | B15: ='AAIP Budget'!G38 -> 411681.25 | C15: ='AAIP Budget'!H38 -> 360297.64 | D15: ='AAIP Budget'!I38 -> 347175.27 | E15: =SUM(B15:D15) -> 1119154.2
A16: AAIP Total | B16: ='AAIP Budget'!G39 -> 1805431.2 | C16: ='AAIP Budget'!H39 -> 1523810.1 | D16: ='AAIP Budget'!I39 -> 1471043.1 | E16: =SUM(B16:D16) -> 4800284.5
A20: Project Rollup | B20: Year 1 | C20: Year 2 | D20: Year 3 | E20: Total
A21: AAIP Lead Organization Budget | B21: ='AAIP Budget'!G39 -> 1805431.2 | C21: ='AAIP Budget'!H39 -> 1523810.1 | D21: ='AAIP Budget'!I39 -> 1471043.1 | E21: ='AAIP Budget'!J39 -> 4800284.5
A22: SGDI Subaward Placeholder | B22: 1300000 | C22: 1350000 | D22: 1300000 | E22: =SUM(B22:D22) -> 3950000
A23: Total Project Budget | B23: =SUM(B21:B22) -> 3105431.2 | C23: =SUM(C21:C22) -> 2873810.1 | D23: =SUM(D21:D22) -> 2771043.1 | E23: =SUM(E21:E22) -> 8750284.5
A25: AAIP Share of Total | E25: =E21/E23 -> 0.54858611
A26: SGDI Share of Total | E26: =E22/E23 -> 0.45141389
A27: NSF Category II Cap | E27: =Assumptions!$B$6 -> 9000000
A28: Amount Below Cap | E28: =E27-E23 -> 249715.47

Sheet AAIP Budget
A1: NSF 26-509 Category II: Indigenous Data Commons | B1: NSF 26-509 Category II: Indigenous Data Commons | C1: NSF 26-509 Category II: Indigenous Data Commons | D1: NSF 26-509 Category II: Indigenous Data Commons | E1: NSF 26-509 Category II: Indigenous Data Commons | F1: NSF 26-509 Category II: Indigenous Data Commons | G1: NSF 26-509 Category II: Indigenous Data Commons | H1: NSF 26-509 Category II: Indigenous Data Commons | I1: NSF 26-509 Category II: Indigenous Data Commons | J1: NSF 26-509 Category II: Indigenous Data Commons
A2: AAIP Lead Organization Budget Planning Worksheet | B2: AAIP Lead Organization Budget Planning Worksheet | C2: AAIP Lead Organization Budget Planning Worksheet | D2: AAIP Lead Organization Budget Planning Worksheet | E2: AAIP Lead Organization Budget Planning Worksheet | F2: AAIP Lead Organization Budget Planning Worksheet | G2: AAIP Lead Organization Budget Planning Worksheet | H2: AAIP Lead Organization Budget Planning Worksheet | I2: AAIP Lead Organization Budget Planning Worksheet | J2: AAIP Lead Organization Budget Planning Worksheet
A3: Planning Target: AAIP as lead organization/national operator; SGDI technical subaward prepared separately. | B3: Planning Target: AAIP as lead organization/national operator; SGDI technical subaward prepared separately. | C3: Planning Target: AAIP as lead organization/national operator; SGDI technical subaward prepared separately. | D3: Planning Target: AAIP as lead organization/national operator; SGDI technical subaward prepared separately. | E3: Planning Target: AAIP as lead organization/national operator; SGDI technical subaward prepared separately. | F3: Planning Target: AAIP as lead organization/national operator; SGDI technical subaward prepared separately. | G3: Planning Target: AAIP as lead organization/national operator; SGDI technical subaward prepared separately. | H3: Planning Target: AAIP as lead organization/national operator; SGDI technical subaward prepared separately. | I3: Planning Target: AAIP as lead organization/national operator; SGDI technical subaward prepared separately. | J3: Planning Target: AAIP as lead organization/national operator; SGDI technical subaward prepared separately.
A5: NSF Line | B5: Budget Category | C5: Budget Holder | D5: Item / Role | E5: FTE / Qty | F5: Rate / Assumption | G5: Year 1 | H5: Year 2 | I5: Year 3 | J5: Total
A6: A | B6: Senior Personnel | C6: AAIP | D6: Principal Investigator / Project Lead | E6: 0.2 | F6: 200000 | G6: =E6*F6 -> 40000 | H6: =G6*(1+Assumptions!$B$4) -> 41200 | I6: =H6*(1+Assumptions!$B$4) -> 42436 | J6: =SUM(G6:I6) -> 123636
A7: A | B7: Senior Personnel | C7: AAIP | D7: Executive Director Oversight | E7: 0.1 | F7: 180000 | G7: =E7*F7 -> 18000 | H7: =G7*(1+Assumptions!$B$4) -> 18540 | I7: =H7*(1+Assumptions!$B$4) -> 19096.2 | J7: =SUM(G7:I7) -> 55636.2
A8: B | B8: Other Personnel | C8: AAIP | D8: Project Director / Operations Manager | E8: 1 | F8: 105000 | G8: =E8*F8 -> 105000 | H8: =G8*(1+Assumptions!$B$4) -> 108150 | I8: =H8*(1+Assumptions!$B$4) -> 111394.5 | J8: =SUM(G8:I8) -> 324544.5
A9: B | B9: Other Personnel | C9: AAIP | D9: Grants & Compliance Manager | E9: 0.6 | F9: 95000 | G9: =E9*F9 -> 57000 | H9: =G9*(1+Assumptions!$B$4) -> 58710 | I9: =H9*(1+Assumptions!$B$4) -> 60471.3 | J9: =SUM(G9:I9) -> 176181.3
A10: B | B10: Other Personnel | C10: AAIP | D10: Finance & Subaward Monitoring Specialist | E10: 0.5 | F10: 80000 | G10: =E10*F10 -> 40000 | H10: =G10*(1+Assumptions!$B$4) -> 41200 | I10: =H10*(1+Assumptions!$B$4) -> 42436 | J10: =SUM(G10:I10) -> 123636
A11: B | B11: Other Personnel | C11: AAIP | D11: Indigenous Data Governance Coordinator | E11: 0.8 | F11: 115000 | G11: =E11*F11 -> 92000 | H11: =G11*(1+Assumptions!$B$4) -> 94760 | I11: =H11*(1+Assumptions!$B$4) -> 97602.8 | J11: =SUM(G11:I11) -> 284362.8
A12: B | B12: Other Personnel | C12: AAIP | D12: Community Engagement & Onboarding Coordinator | E12: 1 | F12: 85000 | G12: =E12*F12 -> 85000 | H12: =G12*(1+Assumptions!$B$4) -> 87550 | I12: =H12*(1+Assumptions!$B$4) -> 90176.5 | J12: =SUM(G12:I12) -> 262726.5
A13: B | B13: Other Personnel | C13: AAIP | D13: Training & Communications Coordinator | E13: 0.75 | F13: 80000 | G13: =E13*F13 -> 60000 | H13: =G13*(1+Assumptions!$B$4) -> 61800 | I13: =H13*(1+Assumptions!$B$4) -> 63654 | J13: =SUM(G13:I13) -> 185454
A14: B | B14: Other Personnel | C14: AAIP | D14: Project Administrative Assistant | E14: 0.5 | F14: 60000 | G14: =E14*F14 -> 30000 | H14: =G14*(1+Assumptions!$B$4) -> 30900 | I14: =H14*(1+Assumptions!$B$4) -> 31827 | J14: =SUM(G14:I14) -> 92727
B15: Subtotal | D15: Total Salaries & Wages | G15: =SUM(G6:G14) -> 527000 | H15: =SUM(H6:H14) -> 542810 | I15: =SUM(I6:I14) -> 559094.3 | J15: =SUM(J6:J14) -> 1628904.3
A16: C | B16: Fringe Benefits | C16: AAIP | D16: Fringe Benefits | F16: Assumptions!B2 | G16: =G15*Assumptions!$B$2 -> 131750 | H16: =H15*Assumptions!$B$2 -> 135702.5 | I16: =I15*Assumptions!$B$2 -> 139773.58 | J16: =SUM(G16:I16) -> 407226.08
A18: E | B18: Travel | C18: AAIP | D18: NSF PI meeting / major cyberinfrastructure conference | F18: Domestic travel | G18: 20000 | H18: 20000 | I18: 20000 | J18: =SUM(G18:I18) -> 60000
A19: E | B19: Travel | C19: AAIP | D19: Partner onboarding and implementation travel | F19: National partner engagement | G19: 35000 | H19: 25000 | I19: 20000 | J19: =SUM(G19:I19) -> 80000
A20: E | B20: Travel | C20: AAIP | D20: Governance, advisory, and training convenings | F20: Domestic travel | G20: 25000 | H20: 20000 | I20: 15000 | J20: =SUM(G20:I20) -> 60000
A21: F | B21: Participant Support | C21: AAIP | D21: Eligible participant support for training/onboarding activities | F21: Stipends/travel/per diem as allowable | G21: 75000 | H21: 75000 | I21: 75000 | J21: =SUM(G21:I21) -> 225000
A22: D | B22: Equipment | C22: AAIP | D22: Limited secure operations/testing/training equipment | F22: Cloud-first; limited equipment only | G22: 75000 | H22: 0 | I22: 0 | J22: =SUM(G22:I22) -> 75000
A23: G.1 | B23: Materials & Supplies | C23: AAIP | D23: Project-specific training, onboarding, and implementation supplies | F23: Supplies below equipment threshold | G23: 20000 | H23: 10000 | I23: 10000 | J23: =SUM(G23:I23) -> 40000
A24: G.2 | B24: Publication/Documentation/Dissemination | C24: AAIP | D24: Documentation, accessibility, dissemination, public reports | F24: Project documentation and dissemination | G24: 20000 | H24: 30000 | I24: 30000 | J24: =SUM(G24:I24) -> 80000
A25: G.3 | B25: Consultant Services | C25: AAIP | D25: Indigenous data sovereignty and governance advisors | F25: Specialized advisor support | G25: 30000 | H25: 20000 | I25: 15000 | J25: =SUM(G25:I25) -> 65000
A26: G.3 | B26: Consultant Services | C26: AAIP | D26: Cybersecurity, privacy, and AI governance consultants | F26: Targeted technical review | G26: 35000 | H26: 25000 | I26: 20000 | J26: =SUM(G26:I26) -> 80000
A27: G.3 | B27: Consultant Services | C27: AAIP | D27: Legal/data use agreement and compliance consultants | F27: Targeted legal/compliance review | G27: 25000 | H27: 15000 | I27: 15000 | J27: =SUM(G27:I27) -> 55000
A28: G.4 | B28: Computer Services | C28: AAIP | D28: Cloud hosting, compute, and operational storage | F28: Managed cloud services | G28: 180000 | H28: 130000 | I28: 110000 | J28: =SUM(G28:I28) -> 420000
A29: G.4 | B29: Computer Services | C29: AAIP | D29: Identity, access, security monitoring, and logging | F29: Security/monitoring services | G29: 65000 | H29: 35000 | I29: 25000 | J29: =SUM(G29:I29) -> 125000
... A35: G.6 | B35: Other Direct Costs | C35: AAIP | D35: Procurement, vendor management, and project administration costs | F35: Direct project administration | G35: 10000 | H35: 5000 | I35: 5000 | J35: =SUM(G35:I35) -> 20000
B36: Subtotal | D36: Total Direct Costs | G36: =SUM(G15:G16,G18:G35) -> 1393750 | H36: =SUM(H15:H16,H18:H35) -> 1163512.5 | I36: =SUM(I15:I16,I18:I35) -> 1123867.9 | J36: =SUM(J15:J16,J18:J35) -> 3681130.4
B37: Indirect Base | D37: Provisional F&A Base (Direct Costs less Equipment and Participant Support) | G37: =G36-G21-G22 -> 1243750 | H37: =H36-H21-H22 -> 1088512.5 | I37: =I36-I21-I22 -> 1048867.9 | J37: =SUM(G37:I37) -> 3381130.4
A38: I | B38: Indirect Costs | C38: AAIP | D38: F&A / Indirect Costs | F38: Assumptions!B3 | G38: =G37*Assumptions!$B$3 -> 411681.25 | H38: =H37*Assumptions!$B$3 -> 360297.64 | I38: =I37*Assumptions!$B$3 -> 347175.27 | J38: =SUM(G38:I38) -> 1119154.2
B39: Total | D39: AAIP Budget Total | G39: =G36+G38 -> 1805431.2 | H39: =H36+H38 -> 1523810.1 | I39: =I36+I38 -> 1471043.1 | J39: =SUM(G39:I39) -> 4800284.5
A41: Note | D41: This AAIP budget excludes the detailed SGDI subaward budget, which will be prepared separately. The project rollup includes an SGDI placeholder for planning.
A42: Note | D42: Final amounts should be revised after confirming AAIP's official federally negotiated indirect cost rate agreement, fringe methodology, NSF budget categories, and subaward treatment.

Sheet Assumptions
A1: Assumption | B1: Value | C1: Notes
A2: Fringe Rate | B2: 0.25 | C2: Planning placeholder; replace with AAIP actual fringe methodology if different.
A3: F&A / Indirect Cost Rate | B3: 0.331 | C3: Planning placeholder based on AAIP estimated federally negotiated rate; confirm rate agreement and base.
A4: Salary Escalation | B4: 0.03 | C4: Annual escalation applied to personnel lines.
A5: SGDI Subaward Placeholder | B5: 3950000 | C5: Separate SGDI subaward budget to be prepared later.
A6: NSF 26-509 Category II Cap | B6: 9000000 | C6: Maximum total project request for Category II.
A7: F&A Exclusion: Equipment | B7: Excluded | C7: Excluded from provisional MTDC base in this planning workbook.
A8: F&A Exclusion: Participant Support | B8: Excluded | C8: Excluded from provisional MTDC base in this planning workbook.

Sheet Cost Estimate View
A1: AAIP Cost Estimate View by Project Work Area | B1: AAIP Cost Estimate View by Project Work Area | C1: AAIP Cost Estimate View by Project Work Area | D1: AAIP Cost Estimate View by Project Work Area | E1: AAIP Cost Estimate View by Project Work Area | F1: AAIP Cost Estimate View by Project Work Area | G1: AAIP Cost Estimate View by Project Work Area
A3: Work Area | B3: Phase / Purpose | C3: Year 1 | D3: Year 2 | E3: Year 3 | F3: Total | G3: Basis of Estimate
A4: Lead Recipient Project Management & Compliance | B4: Award management, finance, procurement, subaward monitoring, reporting | C4: =SUM('AAIP Budget'!G6:G10)+'AAIP Budget'!G35 -> 270000 | D4: =SUM('AAIP Budget'!H6:H10)+'AAIP Budget'!H35 -> 272800 | E4: =SUM('AAIP Budget'!I6:I10)+'AAIP Budget'!I35 -> 280834 | F4: =SUM(C4:E4) -> 823634 | G4: AAIP project leadership, operations, compliance, admin, and finance personnel; related other direct costs.
A5: Indigenous Data Governance & Community Engagement | B5: Governance workflows, data stewardship, partner engagement, advisory coordination | C5: =SUM('AAIP Budget'!G11:G12)+'AAIP Budget'!G20+'AAIP Budget'!G25 -> 232000 | D5: =SUM('AAIP Budget'!H11:H12)+'AAIP Budget'!H20+'AAIP Budget'!H25 -> 222310 | E5: =SUM('AAIP Budget'!I11:I12)+'AAIP Budget'!I20+'AAIP Budget'!I25 -> 217779.3 | F5: =SUM(C5:E5) -> 672089.3 | G5: Governance coordinator, community onboarding coordinator, governance travel, and governance advisor support.
A6: Training, Onboarding & User Engagement | B6: Training logistics, communications, participant support, onboarding convenings | C6: =SUM('AAIP Budget'!G13:G14)+SUM('AAIP Budget'!G18:G19)+'AAIP Budget'!G21+'AAIP Budget'!G24 -> 240000 | D6: =SUM('AAIP Budget'!H13:H14)+SUM('AAIP Budget'!H18:H19)+'AAIP Budget'!H21+'AAIP Budget'!H24 -> 242700 | E6: =SUM('AAIP Budget'!I13:I14)+SUM('AAIP Budget'!I18:I19)+'AAIP Budget'!I21+'AAIP Budget'!I24 -> 240481 | F6: =SUM(C6:E6) -> 723181 | G6: Training/communications personnel, participant support, training travel, and documentation resources.
A7: Infrastructure & Cybersecurity Services | B7: Cloud-first national operations, identity/access, monitoring, backup, AI/API runtime | C7: ='AAIP Budget'!G22+SUM('AAIP Budget'!G28:G32) -> 420000 | D7: ='AAIP Budget'!H22+SUM('AAIP Budget'!H28:H32) -> 220000 | E7: ='AAIP Budget'!I22+SUM('AAIP Budget'!I28:I32) -> 180000 | F7: =SUM(C7:E7) -> 820000 | G7: AAIP-held production cloud, security, logging, backup, platform, and limited equipment costs.
A8: Consultants, Legal, Privacy & AI Governance | B8: Specialized external expertise | C8: =SUM('AAIP Budget'!G26:G27) -> 60000 | D8: =SUM('AAIP Budget'!H26:H27) -> 40000 | E8: =SUM('AAIP Budget'!I26:I27) -> 35000 | F8: =SUM(C8:E8) -> 135000 | G8: Consultants for Indigenous data sovereignty, cybersecurity, privacy, AI governance, and data use agreements.
A9: Documentation & Dissemination | B9: Open documentation, public reports, templates, dissemination | C9: ='AAIP Budget'!G23+'AAIP Budget'!G33+'AAIP Budget'!G34 -> 40000 | D9: ='AAIP Budget'!H23+'AAIP Budget'!H33+'AAIP Budget'!H34 -> 30000 | E9: ='AAIP Budget'!I23+'AAIP Budget'!I33+'AAIP Budget'!I34 -> 30000 | F9: =SUM(C9:E9) -> 100000 | G9: Publication/documentation/dissemination line and accessibility services.
A10: Indirect Costs | B10: AAIP F&A | C10: ='AAIP Budget'!G38 -> 411681.25 | D10: ='AAIP Budget'!H38 -> 360297.64 | E10: ='AAIP Budget'!I38 -> 347175.27 | F10: =SUM(C10:E10) -> 1119154.2 | G10: Calculated using provisional 33.1% rate on provisional base; confirm with AAIP rate agreement.
A12: Total AAIP Cost Estimate | C12: =SUM(C4:C10) -> 1673681.2 | D12: =SUM(D4:D10) -> 1388107.6 | E12: =SUM(E4:E10) -> 1331269.6 | F12: =SUM(F4:F10) -> 4393058.5
