Workbook

Sheet Summary
A1: SGDI Technical Operations Subaward Budget Summary
A2: NSF 26-509 Category II: Indigenous Data Commons
A4: Metric | B4: Amount / Percent | C4: Formula / Source | D4: Notes
A5: SGDI Subaward Budget Total | B5: =C5 -> 3949891.6 | C5: ='SGDI Budget'!J34 -> 3949891.6 | D5: Technical operations subaward planning total.
A6: AAIP Budget Placeholder | B6: =C6 -> 4800285 | C6: =Assumptions!B5 -> 4800285 | D6: AAIP lead organization budget from AAIP planning workbook.
A7: Total Project Planning Amount | B7: =C7 -> 8750176.6 | C7: =B5+B6 -> 8750176.6 | D7: AAIP + SGDI planning total.
A8: SGDI Share of Total | B8: =C8 -> 0.45140707 | C8: =B5/B7 -> 0.45140707 | D8: SGDI technical subaward share.
A9: AAIP Share of Total | B9: =C9 -> 0.54859293 | C9: =B6/B7 -> 0.54859293 | D9: AAIP lead organization share.
A10: Amount Under NSF Category II Cap | B10: =C10 -> 249823.41 | C10: =Assumptions!B6-B7 -> 249823.41 | D10: Planning margin below $9M cap.
A12: Year | B12: SGDI Direct Costs | C12: SGDI Indirect Costs | D12: SGDI Total | E12: Primary Focus
A13: Year 1 | B13: ='SGDI Budget'!G31 -> 1168265 | C13: ='SGDI Budget'!G33 -> 113826.5 | D13: ='SGDI Budget'!G34 -> 1282091.5 | E13: Transition to operations, early data pipelines, AI/MCP service operationalization, onboarding support
A14: Year 2 | B14: ='SGDI Budget'!H31 -> 1201502.9 | C14: ='SGDI Budget'!H33 -> 119150.29 | D14: ='SGDI Budget'!H34 -> 1320653.2 | E14: National scale-up, expanded data connectors, dashboards, training, user support
A15: Year 3 | B15: ='SGDI Budget'!I31 -> 1225588 | C15: ='SGDI Budget'!I33 -> 121558.8 | D15: ='SGDI Budget'!I34 -> 1347146.8 | E15: Mature operations, optimization, evaluation, documentation, sustainability planning

Sheet SGDI Budget
A1: NSF 26-509 Category II: Indigenous Data Commons
A2: SGDI Technical Operations Subaward Budget Planning Worksheet
A3: Planning Target: SGDI technical personnel, AI/MCP services, data engineering, analytics, evaluation, documentation, and technical user support. Major production infrastructure held by AAIP.
A5: NSF Line | B5: Budget Category | C5: Budget Holder | D5: Item / Role | E5: FTE / Qty | F5: Rate / Assumption | G5: Year 1 | H5: Year 2 | I5: Year 3 | J5: Total
A6: A | B6: Senior Personnel | C6: SGDI | D6: Technical Director / IDC Architect | E6: 0.5 | F6: 190000 | G6: =E6*F6 -> 95000 | H6: =G6*(1+Assumptions!$B$4) -> 97850 | I6: =H6*(1+Assumptions!$B$4) -> 100785.5 | J6: =SUM(G6:I6) -> 293635.5
A7: B | B7: Other Personnel | C7: SGDI | D7: Technical Project Manager / Data Operations Lead | E7: 0.6 | F7: 115000 | G7: =E7*F7 -> 69000 | H7: =G7*(1+Assumptions!$B$4) -> 71070 | I7: =H7*(1+Assumptions!$B$4) -> 73202.1 | J7: =SUM(G7:I7) -> 213272.1
A8: B | B8: Other Personnel | C8: SGDI | D8: Data Engineer | E8: 1 | F8: 130000 | G8: =E8*F8 -> 130000 | H8: =G8*(1+Assumptions!$B$4) -> 133900 | I8: =H8*(1+Assumptions!$B$4) -> 137917 | J8: =SUM(G8:I8) -> 401817
A9: B | B9: Other Personnel | C9: SGDI | D9: Data Scientist / Analytics Lead | E9: 0.8 | F9: 125000 | G9: =E9*F9 -> 100000 | H9: =G9*(1+Assumptions!$B$4) -> 103000 | I9: =H9*(1+Assumptions!$B$4) -> 106090 | J9: =SUM(G9:I9) -> 309090
A10: B | B10: Other Personnel | C10: SGDI | D10: AI / MCP Services Engineer | E10: 1 | F10: 145000 | G10: =E10*F10 -> 145000 | H10: =G10*(1+Assumptions!$B$4) -> 149350 | I10: =H10*(1+Assumptions!$B$4) -> 153830.5 | J10: =SUM(G10:I10) -> 448180.5
A11: B | B11: Other Personnel | C11: SGDI | D11: Evaluation Director | E11: 0.5 | F11: 120000 | G11: =E11*F11 -> 60000 | H11: =G11*(1+Assumptions!$B$4) -> 61800 | I11: =H11*(1+Assumptions!$B$4) -> 63654 | J11: =SUM(G11:I11) -> 185454
A12: B | B12: Other Personnel | C12: SGDI | D12: User Support & Training Specialist | E12: 0.9 | F12: 85000 | G12: =E12*F12 -> 76500 | H12: =G12*(1+Assumptions!$B$4) -> 78795 | I12: =H12*(1+Assumptions!$B$4) -> 81158.85 | J12: =SUM(G12:I12) -> 236453.85
A13: B | B13: Other Personnel | C13: SGDI | D13: Database / Cloud Support Specialist | E13: 0.5 | F13: 130000 | G13: =E13*F13 -> 65000 | H13: =G13*(1+Assumptions!$B$4) -> 66950 | I13: =H13*(1+Assumptions!$B$4) -> 68958.5 | J13: =SUM(G13:I13) -> 200908.5
A14: B | B14: Other Personnel | C14: SGDI | D14: Technical Writer / Documentation Specialist | E14: 0.35 | F14: 80000 | G14: =E14*F14 -> 28000 | H14: =G14*(1+Assumptions!$B$4) -> 28840 | I14: =H14*(1+Assumptions!$B$4) -> 29705.2 | J14: =SUM(G14:I14) -> 86545.2
A15: B | B15: Other Personnel | C15: SGDI | D15: Grant Reporting & Analytics Specialist | E15: 0.4 | F15: 90000 | G15: =E15*F15 -> 36000 | H15: =G15*(1+Assumptions!$B$4) -> 37080 | I15: =H15*(1+Assumptions!$B$4) -> 38192.4 | J15: =SUM(G15:I15) -> 111272.4
B16: Subtotal | D16: Total Salaries & Wages | G16: =SUM(G6:G15) -> 804500 | H16: =SUM(H6:H15) -> 828635 | I16: =SUM(I6:I15) -> 853494.05 | J16: =SUM(J6:J15) -> 2486629.1
A17: C | B17: Fringe Benefits | C17: SGDI | D17: Fringe Benefits | F17: Assumptions!B2 | G17: =G16*Assumptions!$B$2 -> 136765 | H17: =H16*Assumptions!$B$2 -> 140867.95 | I17: =I16*Assumptions!$B$2 -> 145093.99 | J17: =SUM(G17:I17) -> 422726.94
A19: E | B19: Travel | C19: SGDI | D19: NSF PI meeting / major cyberinfrastructure conference | F19: Domestic travel | G19: 12000 | H19: 12000 | I19: 12000 | J19: =SUM(G19:I19) -> 36000
A20: E | B20: Travel | C20: SGDI | D20: Technical onboarding and implementation travel | F20: Partner implementation support | G20: 30000 | H20: 35000 | I20: 30000 | J20: =SUM(G20:I20) -> 95000
A21: E | B21: Travel | C21: SGDI | D21: Training workshops / partner technical support travel | F21: Training and technical assistance | G21: 20000 | H21: 25000 | I21: 25000 | J21: =SUM(G21:I21) -> 70000
A22: D | B22: Equipment | C22: SGDI | D22: Limited development, security, and testing equipment | F22: Special-purpose project equipment | G22: 30000 | H22: 10000 | I22: 10000 | J22: =SUM(G22:I22) -> 50000
A23: G.1 | B23: Materials & Supplies | C23: SGDI | D23: Project-specific technical supplies and training materials | F23: Supplies below equipment threshold | G23: 8000 | H23: 8000 | I23: 8000 | J23: =SUM(G23:I23) -> 24000
A24: G.2 | B24: Publication/Documentation/Dissemination | C24: SGDI | D24: Technical documentation, workflow guides, and dissemination | F24: Documentation and dissemination | G24: 15000 | H24: 20000 | I24: 25000 | J24: =SUM(G24:I24) -> 60000
A25: G.3 | B25: Consultant Services | C25: SGDI | D25: Specialized security, AI, and architecture review | F25: Targeted expert review | G25: 20000 | H25: 20000 | I25: 20000 | J25: =SUM(G25:I25) -> 60000
A26: G.3 | B26: Consultant Services | C26: SGDI | D26: UX, accessibility, and data governance technical consultants | F26: Targeted implementation review | G26: 10000 | H26: 10000 | I26: 10000 | J26: =SUM(G26:I26) -> 30000
A27: G.4 | B27: Computer Services | C27: SGDI | D27: Development/test cloud and sandbox services | F27: Development and test environments | G27: 30000 | H27: 35000 | I27: 35000 | J27: =SUM(G27:I27) -> 100000
A28: G.4 | B28: Computer Services | C28: SGDI | D28: Software, developer tools, and data quality tooling | F28: Technical tools and services | G28: 35000 | H28: 40000 | I28: 40000 | J28: =SUM(G28:I28) -> 115000
A29: G.4 | B29: Computer Services | C29: SGDI | D29: Security testing and code review support | F29: Testing and review services | G29: 5000 | H29: 5000 | I29: 0 | J29: =SUM(G29:I29) -> 10000
A30: G.6 | B30: Other Direct Costs | C30: SGDI | D30: QA/testing, documentation platforms, and technical collaboration services | F30: Technical operations support | G30: 12000 | H30: 12000 | I30: 12000 | J30: =SUM(G30:I30) -> 36000
B31: Subtotal | D31: Total Direct Costs | G31: =SUM(G16:G17,G19:G30) -> 1168265 | H31: =SUM(H16:H17,H19:H30) -> 1201502.9 | I31: =SUM(I16:I17,I19:I30) -> 1225588 | J31: =SUM(J16:J17,J19:J30) -> 3595356
B32: Indirect Base | D32: Provisional Indirect Base (Direct Costs less Equipment) | G32: =G31-G22 -> 1138265 | H32: =H31-H22 -> 1191502.9 | I32: =I31-I22 -> 1215588 | J32: =SUM(G32:I32) -> 3545356
A33: I | B33: Indirect Costs | C33: SGDI | D33: Indirect / Overhead Costs | F33: Assumptions!B3 | G33: =G32*Assumptions!$B$3 -> 113826.5 | H33: =H32*Assumptions!$B$3 -> 119150.29 | I33: =I32*Assumptions!$B$3 -> 121558.8 | J33: =SUM(G33:I33) -> 354535.6
B34: Total | D34: SGDI Subaward Budget Total | G34: =G31+G33 -> 1282091.5 | H34: =H31+H33 -> 1320653.2 | I34: =I31+I33 -> 1347146.8 | J34: =SUM(G34:I34) -> 3949891.6
A36: Note | D36: Major production infrastructure contracts, cloud services, cybersecurity services, identity/access systems, and lead-recipient operations are assumed to be managed by AAIP. SGDI budget includes technical personnel and development/test services needed to perform the subaward scope.
A37: Note | D37: Final amounts should be revised after AAIP subrecipient review, SGDI payroll/fringe verification, and confirmation of allowable indirect/overhead treatment.

Sheet Assumptions
A1: Assumption | B1: Value | C1: Notes
A2: SGDI Fringe Rate | B2: 0.17 | C2: Planning assumption; replace with SGDI actual fringe methodology.
A3: SGDI Indirect / Overhead Rate | B3: 0.1 | C3: Planning assumption; final rate subject to AAIP subrecipient review and applicable requirements.
A4: Annual Salary Escalation | B4: 0.03 | C4: Planning assumption for Year 2 and Year 3 salaries.
A5: AAIP Budget Placeholder | B5: 4800285 | C5: AAIP lead budget from AAIP planning workbook; update after AAIP finalizes budget.
A6: NSF Category II Cap | B6: 9000000 | C6: NSF 26-509 Category II maximum total project amount.
A7: SGDI Target Range | B7: 3950000 | C7: Planning target for SGDI technical operations subaward.
A8: Production Infrastructure Holder | B8: AAIP | C8: Major production cloud, cybersecurity, identity, and infrastructure contracts are assumed to be held by AAIP.

Sheet Cost Estimate View
A1: SGDI Detailed Cost Estimate View by Budget Area
A3: Work Area | B3: Lead Entity | C3: Year 1 | D3: Year 2 | E3: Year 3 | F3: Total | G3: Notes
A4: Personnel & Fringe | B4: SGDI | C4: ='SGDI Budget'!G16+'SGDI Budget'!G17 -> 941265 | D4: ='SGDI Budget'!H16+'SGDI Budget'!H17 -> 969502.95 | E4: ='SGDI Budget'!I16+'SGDI Budget'!I17 -> 998588.04 | F4: =SUM(C4:E4) -> 2909356 | G4: Technical staffing and fringe for data engineering, AI/MCP services, analytics, evaluation, support, and documentation.
A5: Travel & Technical Onboarding | B5: SGDI | C5: =SUM('SGDI Budget'!G19:G21) -> 62000 | D5: =SUM('SGDI Budget'!H19:H21) -> 72000 | E5: =SUM('SGDI Budget'!I19:I21) -> 67000 | F5: =SUM(C5:E5) -> 201000 | G5: NSF/cyberinfrastructure meetings, partner technical onboarding, training, and implementation travel.
A6: Equipment | B6: SGDI | C6: ='SGDI Budget'!G22 -> 30000 | D6: ='SGDI Budget'!H22 -> 10000 | E6: ='SGDI Budget'!I22 -> 10000 | F6: =SUM(C6:E6) -> 50000 | G6: Limited development, security, and testing equipment.
A7: Supplies, Documentation, and Dissemination | B7: SGDI | C7: =SUM('SGDI Budget'!G23:G24,'SGDI Budget'!G30) -> 35000 | D7: =SUM('SGDI Budget'!H23:H24,'SGDI Budget'!H30) -> 40000 | E7: =SUM('SGDI Budget'!I23:I24,'SGDI Budget'!I30) -> 45000 | F7: =SUM(C7:E7) -> 120000 | G7: Technical supplies, project documentation, workflow guides, dissemination, QA/testing and collaboration services.
A8: Consultants and Security Review | B8: SGDI | C8: =SUM('SGDI Budget'!G25:G26,'SGDI Budget'!G29) -> 35000 | D8: =SUM('SGDI Budget'!H25:H26,'SGDI Budget'!H29) -> 35000 | E8: =SUM('SGDI Budget'!I25:I26,'SGDI Budget'!I29) -> 30000 | F8: =SUM(C8:E8) -> 100000 | G8: Specialized security, AI, architecture, UX, accessibility, and data governance technical review.
A9: Computer Services and Technical Tools | B9: SGDI | C9: =SUM('SGDI Budget'!G27:G28) -> 65000 | D9: =SUM('SGDI Budget'!H27:H28) -> 75000 | E9: =SUM('SGDI Budget'!I27:I28) -> 75000 | F9: =SUM(C9:E9) -> 215000 | G9: Development/test cloud, sandbox services, software, developer tools, and data quality tooling.
A10: Indirect / Overhead | B10: SGDI | C10: ='SGDI Budget'!G33 -> 113826.5 | D10: ='SGDI Budget'!H33 -> 119150.29 | E10: ='SGDI Budget'!I33 -> 121558.8 | F10: =SUM(C10:E10) -> 354535.6 | G10: Provisional subaward indirect/overhead estimate.
A11: Total | B11: SGDI | C11: =SUM(C4:C10) -> 1282091.5 | D11: =SUM(D4:D10) -> 1320653.2 | E11: =SUM(E4:E10) -> 1347146.8 | F11: =SUM(F4:F10) -> 3949891.6 | G11: Should match SGDI Subaward Budget Total.
